oxlang/__init__.py
oxlang/__version__.py
oxlang/_scorpion.py
oxlang/ast_.py
oxlang/exceptions.py
oxlang/repl.py
oxlang/runtime.py
oxlang/syntax.py
oxlang/stdlib/math.ox
oxlang-0.0.1a0.dist-info/entry_points.txt
oxlang-0.0.1a0.dist-info/WHEEL
oxlang-0.0.1a0.dist-info/METADATA
oxlang-0.0.1a0.dist-info/RECORD
