Metadata-Version: 2.1
Name: oxlang
Version: 0.0.1a0
Summary: Python implementation of ox.
Home-page: https://github.com/ongyx/ox
Author: Ong Yong Xin
Author-email: ongyongxin2020+github@gmail.com
Requires-Python: >=3.6
Classifier: Programming Language :: Python :: 3
Classifier: License :: OSI Approved :: MIT License
Classifier: Operating System :: OS Independent
Requires-Dist: sly>=0.4
Requires-Dist: pytest>=6.2.2 ; extra == "test"
Provides-Extra: test
